google_books_api_wrapper/__init__.py
google_books_api_wrapper/_rest_adapter.py
google_books_api_wrapper/api.py
google_books_api_wrapper/constants.py
google_books_api_wrapper/exceptions.py
google_books_api_wrapper/models.py
google_books_api_wrapper-1.0.3.dist-info/WHEEL
google_books_api_wrapper-1.0.3.dist-info/METADATA
google_books_api_wrapper-1.0.3.dist-info/LICENSE
google_books_api_wrapper-1.0.3.dist-info/RECORD
