Metadata-Version: 2.1
Name: google-books-api-wrapper
Version: 1.0.3
Summary: A simple and easy to use wrapper around the Google Books Web API.
Home-page: https://github.com/dankrzeminski32/google-books-api-wrapper
License: MIT
Author: dankrzeminski32
Author-email: dankrzeminski32@gmail.com
Requires-Python: >=3.10,<4.0
Classifier: License :: OSI Approved :: MIT License
Classifier: Programming Language :: Python :: 3
Classifier: Programming Language :: Python :: 3.10
Classifier: Programming Language :: Python :: 3.11
Requires-Dist: certifi (==2022.12.7)
Requires-Dist: charset-normalizer (==3.0.1)
Requires-Dist: idna (==3.4)
Requires-Dist: requests (==2.28.2)
Requires-Dist: urllib3 (==1.26.14)
Project-URL: Documentation, https://dankrzeminski32.github.io/google-books-api-wrapper/
